frida_hooks/__init__.py
frida_hooks/agent.py
frida_hooks/colors.py
frida_hooks/httphandler.py
frida_hooks/main.py
frida_hooks/scriptor.py
frida_hooks/scripts.js
frida_hooks/utils.py
frida_hooks/bin/SoFixer-Windows-32.exe
frida_hooks/bin/SoFixer-Windows-64.exe
frida_hooks-0.9.16.dist-info/LICENSE
frida_hooks-0.9.16.dist-info/METADATA
frida_hooks-0.9.16.dist-info/WHEEL
frida_hooks-0.9.16.dist-info/entry_points.txt
frida_hooks-0.9.16.dist-info/top_level.txt
frida_hooks-0.9.16.dist-info/RECORD
