Metadata-Version: 2.1
Name: frida-hooks
Version: 0.9.16
Summary: Dynamic instrumentation toolkits powered by Frida
Home-page: https://github.com/softice70/frida-hooks
Author: Ryan
Author-email: dawnsun@sina.com
License: Apache License, Version 2.0
Platform: UNKNOWN
License-File: LICENSE
